sciapy/__init__.py
sciapy/plot_setup.py
sciapy/data/indices/AE_Kyoto_1980-2016_daily_shift12h.dat
sciapy/data/indices/AE_Kyoto_1980-2018_daily2_shift12h.dat
sciapy/data/indices/f107_noontime_flux_obs.txt
sciapy/data/indices/f107a_noontime_flux_obs.txt
sciapy/data/indices/lisird_lya3_1980-2021.dat
sciapy/data/indices/lisird_lya_version3_daily_full.dat
sciapy/data/indices/spidr_ap_2000-2012.dat
sciapy/data/indices/spidr_f107_2000-2012.dat
sciapy/data/indices/spidr_kp_2000-2012.dat
sciapy/level1c/__init__.py
sciapy/level1c/_types.py
sciapy/level1c/scia_limb.py
sciapy/level1c/scia_limb_hdf5.py
sciapy/level1c/scia_limb_mpl.py
sciapy/level1c/scia_limb_nc.py
sciapy/level1c/scia_limb_txt.py
sciapy/level1c/scia_solar.py
sciapy/level2/AACGM2005_80km_grid.nc
sciapy/level2/IGRF.tab
sciapy/level2/__init__.py
sciapy/level2/aacgm2005.py
sciapy/level2/binning.py
sciapy/level2/density.py
sciapy/level2/density_pp.py
sciapy/level2/igrf.py
sciapy/level2/post_process.py
sciapy/level2/scia_akm.py
sciapy/regress/__init__.py
sciapy/regress/__main__.py
sciapy/regress/_gpkernels.py
sciapy/regress/_options.py
sciapy/regress/_plot.py
sciapy/regress/load_data.py
sciapy/regress/mcmc.py
sciapy/regress/statistics.py
sciapy-0.0.8.data/scripts/scia_binary_util.py
sciapy-0.0.8.data/scripts/scia_conv_hdf5_limb.py
sciapy-0.0.8.data/scripts/scia_daily_zonal_mean.py
sciapy-0.0.8.data/scripts/scia_post_process_l2.py
sciapy-0.0.8.dist-info/LICENSE
sciapy-0.0.8.dist-info/METADATA
sciapy-0.0.8.dist-info/WHEEL
sciapy-0.0.8.dist-info/entry_points.txt
sciapy-0.0.8.dist-info/top_level.txt
sciapy-0.0.8.dist-info/RECORD
