Metadata-Version: 2.1
Name: sciapy
Version: 0.0.8
Summary: Python tools for (some) SCIAMACHY data
Home-page: http://github.com/st-bender/sciapy
Author: Stefan Bender
Author-email: stefan.bender@ntnu.no
License: GPLv2
Classifier: Development Status :: 3 - Alpha
Classifier: Intended Audience :: Science/Research
Classifier: License :: OSI Approved :: GNU General Public License v2 (GPLv2)
Classifier: Programming Language :: Python
Classifier: Programming Language :: Python :: 2
Classifier: Programming Language :: Python :: 2.7
Classifier: Programming Language :: Python :: 3
Classifier: Programming Language :: Python :: 3.4
Classifier: Programming Language :: Python :: 3.5
Classifier: Programming Language :: Python :: 3.6
Classifier: Programming Language :: Python :: 3.7
Classifier: Programming Language :: Python :: 3.8
License-File: LICENSE
Requires-Dist: numpy (>=1.13.0)
Requires-Dist: scipy (>=0.17.0)
Requires-Dist: matplotlib (>=2.2)
Requires-Dist: netCDF4
Requires-Dist: h5py
Requires-Dist: dask
Requires-Dist: toolz
Requires-Dist: astropy
Requires-Dist: pandas
Requires-Dist: xarray
Requires-Dist: parse
Requires-Dist: autograd
Requires-Dist: celerite (>=0.3.0)
Requires-Dist: corner
Requires-Dist: george
Requires-Dist: emcee
Requires-Dist: regressproxy
Provides-Extra: all
Requires-Dist: nrlmsise00 ; extra == 'all'
Requires-Dist: pytest ; extra == 'all'
Provides-Extra: msis
Requires-Dist: nrlmsise00 ; extra == 'msis'
Provides-Extra: tests
Requires-Dist: nrlmsise00 ; extra == 'tests'
Requires-Dist: pytest ; extra == 'tests'
